BuddyAssistant/Assistant.py
BuddyAssistant/BuddyAssistant.py
BuddyAssistant/__init__.py
BuddyAssistant/storage/__init__.py
BuddyAssistant/storage/base_storage.py
BuddyAssistant/storage/local_storage.py
BuddyAssistant/storage/models.py
BuddyAssistant/storage/mysql_storage.py
BuddyAssistant/storage/postgres_storage.py
BuddyAssistant/storage/s3_storage.py
BuddyAssistant/tests/__init__.py
BuddyAssistant/tests/test_assistant.py
BuddyAssistant/tests/storage/__init__.py
BuddyAssistant/tests/storage/test_local_storage.py
BuddyAssistant/tests/storage/test_mysql_storage.py
BuddyAssistant/tests/storage/test_postgres_storage.py
BuddyAssistant/tests/storage/test_s3_storage.py
storage/__init__.py
storage/base_storage.py
storage/local_storage.py
storage/models.py
storage/mysql_storage.py
storage/postgres_storage.py
storage/s3_storage.py
tests/__init__.py
tests/test_assistant.py
tests/storage/__init__.py
tests/storage/test_local_storage.py
tests/storage/test_mysql_storage.py
tests/storage/test_postgres_storage.py
tests/storage/test_s3_storage.py
BuddyAssistant-0.1.7.dist-info/LICENSE
BuddyAssistant-0.1.7.dist-info/METADATA
BuddyAssistant-0.1.7.dist-info/WHEEL
BuddyAssistant-0.1.7.dist-info/top_level.txt
BuddyAssistant-0.1.7.dist-info/RECORD
