Metadata-Version: 2.1
Name: BuddyAssistant
Version: 0.1.7
Summary: BuddyAssistant is a conversational AI assistant.
Home-page: https://github.com/anislangar/buddyassistant
Author: Anis Langar
Author-email: anisd116@gmail.com
License: MIT
Requires-Python: >=3.6
License-File: LICENSE
